Workbook

Sheet Executive Dashboard
A1: FINANCIAL PERFORMANCE | FY2026
A2: Executive management dashboard • RM million unless noted • fictional demonstration
A4: REVENUE ACTUAL | D4: REVENUE VS BUDGET | G4: GROSS PROFIT | J4: GP MARGIN
A5: ='Monthly Performance'!C17/1000000 -> 217.24 | D5: ='Monthly Performance'!E17 -> 0.00036787142 | G5: ='Monthly Performance'!J17/1000000 -> 51.386 | J5: ='Monthly Performance'!L17 -> 0.23654023
A8: BUDGET REVENUE | D8: REVENUE FORECAST | G8: EBITDA PROXY | J8: FORECAST VARIANCE
A9: ='Monthly Performance'!B17/1000000 -> 217.16011 | D9: ='Monthly Performance'!N17/1000000 -> 219.14 | G9: ='Monthly Performance'!M17/1000000 -> 51.386 | J9: ='Monthly Performance'!O17 -> -0.0086702565
A13: Month | B13: Budget RMm | C13: Actual RMm | D13: Forecast RMm | E13: GP RMm | G13: Management insights | H13: Metric | I13: Value | J13: Interpretation
A14: ='Monthly Performance'!A4 -> Jan | B14: ='Monthly Performance'!B4/1000000 -> 16.282605 | C14: ='Monthly Performance'!C4/1000000 -> 16.639 | D14: ='Monthly Performance'!N4/1000000 -> 16.282 | E14: ='Monthly Performance'!J4/1000000 -> 3.53 | G14: Revenue delivery | H14: Actual / budget | I14: ='Monthly Performance'!E17 -> 0.00036787142 | J14: Positive indicates outperformance
A15: ='Monthly Performance'!A5 -> Feb | B15: ='Monthly Performance'!B5/1000000 -> 16.753705 | C15: ='Monthly Performance'!C5/1000000 -> 15.433 | D15: ='Monthly Performance'!N5/1000000 -> 17.155 | E15: ='Monthly Performance'!J5/1000000 -> 3.272 | G15: Gross profit | H15: Actual RMm | I15: ='Monthly Performance'!J17/1000000 -> 51.386 | J15: GP after direct costs (not vs budget)
A16: ='Monthly Performance'!A6 -> Mar | B16: ='Monthly Performance'!B6/1000000 -> 16.325623 | C16: ='Monthly Performance'!C6/1000000 -> 16.667 | D16: ='Monthly Performance'!N6/1000000 -> 16.131 | E16: ='Monthly Performance'!J6/1000000 -> 4.515 | G16: Margin quality | H16: GP margin | I16: ='Monthly Performance'!L17 -> 0.23654023 | J16: Gross profit / revenue
A17: ='Monthly Performance'!A7 -> Apr | B17: ='Monthly Performance'!B7/1000000 -> 17.415484 | C17: ='Monthly Performance'!C7/1000000 -> 17.008 | D17: ='Monthly Performance'!N7/1000000 -> 17.883 | E17: ='Monthly Performance'!J7/1000000 -> 4.425 | G17: Cost discipline | H17: Cost variance RMm | I17: ='Monthly Performance'!H17/1000000 -> -0.247 | J17: Positive = cost below budget
A18: ='Monthly Performance'!A8 -> May | B18: ='Monthly Performance'!B8/1000000 -> 17.607496 | C18: ='Monthly Performance'!C8/1000000 -> 17.957 | D18: ='Monthly Performance'!N8/1000000 -> 17.647 | E18: ='Monthly Performance'!J8/1000000 -> 4.695 | G18: Forecast accuracy | H18: Actual vs forecast | I18: ='Monthly Performance'!O17 -> -0.0086702565 | J18: Closer to zero = more accurate
A19: ='Monthly Performance'!A9 -> Jun | B19: ='Monthly Performance'!B9/1000000 -> 18.631161 | C19: ='Monthly Performance'!C9/1000000 -> 18.911 | D19: ='Monthly Performance'!N9/1000000 -> 18.291 | E19: ='Monthly Performance'!J9/1000000 -> 3.985
A20: ='Monthly Performance'!A10 -> Jul | B20: ='Monthly Performance'!B10/1000000 -> 18.632127 | C20: ='Monthly Performance'!C10/1000000 -> 18.992 | D20: ='Monthly Performance'!N10/1000000 -> 19.152 | E20: ='Monthly Performance'!J10/1000000 -> 5.036
A21: ='Monthly Performance'!A11 -> Aug | B21: ='Monthly Performance'!B11/1000000 -> 17.91851 | C21: ='Monthly Performance'!C11/1000000 -> 16.857 | D21: ='Monthly Performance'!N11/1000000 -> 18.49 | E21: ='Monthly Performance'!J11/1000000 -> 3.758 | G21: MANAGEMENT COMMENTARY
A22: ='Monthly Performance'!A12 -> Sep | B22: ='Monthly Performance'!B12/1000000 -> 18.974611 | C22: ='Monthly Performance'!C12/1000000 -> 20.04 | D22: ='Monthly Performance'!N12/1000000 -> 19.225 | E22: ='Monthly Performance'!J12/1000000 -> 4.647 | G22: =IF('Monthly Performance'!D17>=0,"REVENUE | RM "&TEXT('Monthly Performance'!D17/1000000,"0.00")&"m above budget ("&TEXT('Monthly Performance'!E17,"0.00%")&"); broadly on plan.","REVENUE | RM "&TEXT(ABS('Monthly Performance'!D17)/1000000,"0.00")&"m below budget ("&TEXT(ABS('Monthly Performance'!E17),"0.00%")&"); review shortfall.") -> REVENUE | RM 0.08m above budget (0.04%); broadly on plan.
A23: ='Monthly Performance'!A13 -> Oct | B23: ='Monthly Performance'!B13/1000000 -> 19.648856 | C23: ='Monthly Performance'!C13/1000000 -> 20.8 | D23: ='Monthly Performance'!N13/1000000 -> 20.255 | E23: ='Monthly Performance'!J13/1000000 -> 4.665 | G23: =IF('Monthly Performance'!H17<0,"COST & GP | Cost overrun RM "&TEXT(ABS('Monthly Performance'!H17)/1000000,"0.00")&"m; GP "&IF('Monthly Performance'!K17<0,"below","above")&" budget by RM "&TEXT(ABS('Monthly Performance'!K17)/1000000,"0.00")&"m.","COST & GP | Costs below budget by RM "&TEXT('Monthly Performance'!H17/1000000,"0.00")&"m; GP variance RM "&TEXT('Monthly Performance'!K17/1000000,"0.00")&"m.") -> COST & GP | Cost overrun RM 0.25m; GP below budget by RM 0.17m.
A24: ='Monthly Performance'!A14 -> Nov | B24: ='Monthly Performance'!B14/1000000 -> 18.962586 | C24: ='Monthly Performance'!C14/1000000 -> 17.582 | D24: ='Monthly Performance'!N14/1000000 -> 18.555 | E24: ='Monthly Performance'!J14/1000000 -> 3.915 | G24: =IF(ABS('Monthly Performance'!O17)<0.01,"ACTION | Review high-cost projects and refresh forecast assumptions; forecast gap "&TEXT(ABS('Monthly Performance'!O17),"0.0%")&".","ACTION | Investigate cost drivers, validate revenue milestones and refresh forecast; gap "&TEXT(ABS('Monthly Performance'!O17),"0.0%")&".") -> ACTION | Review high-cost projects and refresh forecast assumptions; forecast gap 0.9%.
A25: ='Monthly Performance'!A15 -> Dec | B25: ='Monthly Performance'!B15/1000000 -> 20.007349 | C25: ='Monthly Performance'!C15/1000000 -> 20.354 | D25: ='Monthly Performance'!N15/1000000 -> 20.074 | E25: ='Monthly Performance'!J15/1000000 -> 4.943
A29: Methodology: GP = revenue − illustrative modeled costs. EBITDA proxy equals GP because no separate operating expense categories are modeled.
A30: Portfolio disclaimer: No employer, client or confidential financial data used.

Sheet Monthly Performance
A1: FY2026 | MONTHLY PERFORMANCE ANALYSIS
A3: Month | B3: Rev Budget | C3: Rev Actual | D3: Rev Var RM | E3: Rev Var % | F3: Cost Budget | G3: Cost Actual | H3: Cost Var RM | I3: GP Budget | J3: GP Actual | K3: GP Var RM | L3: GP Margin | M3: EBITDA Proxy | N3: Rev Forecast | O3: Forecast Var %
A4: ='Fictional Inputs'!A4 -> Jan | B4: ='Fictional Inputs'!B4 -> 16282605 | C4: ='Fictional Inputs'!C4 -> 16639000 | D4: =C4-B4 -> 356395 | E4: =IFERROR(D4/B4,0) -> 0.021888082 | F4: ='Fictional Inputs'!D4 -> 12112000 | G4: ='Fictional Inputs'!E4 -> 13109000 | H4: =F4-G4 -> -997000 | I4: =B4-F4 -> 4170605 | J4: =C4-G4 -> 3530000 | K4: =J4-I4 -> -640605 | L4: =IFERROR(J4/C4,0) -> 0.21215217 | M4: =J4 -> 3530000 | N4: ='Fictional Inputs'!F4 -> 16282000 | O4: =IFERROR((C4-N4)/N4,0) -> 0.021926053
A5: ='Fictional Inputs'!A5 -> Feb | B5: ='Fictional Inputs'!B5 -> 16753705 | C5: ='Fictional Inputs'!C5 -> 15433000 | D5: =C5-B5 -> -1320705 | E5: =IFERROR(D5/B5,0) -> -0.078830623 | F5: ='Fictional Inputs'!D5 -> 12453000 | G5: ='Fictional Inputs'!E5 -> 12161000 | H5: =F5-G5 -> 292000 | I5: =B5-F5 -> 4300705 | J5: =C5-G5 -> 3272000 | K5: =J5-I5 -> -1028705 | L5: =IFERROR(J5/C5,0) -> 0.21201322 | M5: =J5 -> 3272000 | N5: ='Fictional Inputs'!F5 -> 17155000 | O5: =IFERROR((C5-N5)/N5,0) -> -0.1003789
A6: ='Fictional Inputs'!A6 -> Mar | B6: ='Fictional Inputs'!B6 -> 16325623 | C6: ='Fictional Inputs'!C6 -> 16667000 | D6: =C6-B6 -> 341377 | E6: =IFERROR(D6/B6,0) -> 0.020910504 | F6: ='Fictional Inputs'!D6 -> 12503000 | G6: ='Fictional Inputs'!E6 -> 12152000 | H6: =F6-G6 -> 351000 | I6: =B6-F6 -> 3822623 | J6: =C6-G6 -> 4515000 | K6: =J6-I6 -> 692377 | L6: =IFERROR(J6/C6,0) -> 0.27089458 | M6: =J6 -> 4515000 | N6: ='Fictional Inputs'!F6 -> 16131000 | O6: =IFERROR((C6-N6)/N6,0) -> 0.033227946
A7: ='Fictional Inputs'!A7 -> Apr | B7: ='Fictional Inputs'!B7 -> 17415484 | C7: ='Fictional Inputs'!C7 -> 17008000 | D7: =C7-B7 -> -407484 | E7: =IFERROR(D7/B7,0) -> -0.023397799 | F7: ='Fictional Inputs'!D7 -> 12924000 | G7: ='Fictional Inputs'!E7 -> 12583000 | H7: =F7-G7 -> 341000 | I7: =B7-F7 -> 4491484 | J7: =C7-G7 -> 4425000 | K7: =J7-I7 -> -66484 | L7: =IFERROR(J7/C7,0) -> 0.26017168 | M7: =J7 -> 4425000 | N7: ='Fictional Inputs'!F7 -> 17883000 | O7: =IFERROR((C7-N7)/N7,0) -> -0.048929151
A8: ='Fictional Inputs'!A8 -> May | B8: ='Fictional Inputs'!B8 -> 17607496 | C8: ='Fictional Inputs'!C8 -> 17957000 | D8: =C8-B8 -> 349504 | E8: =IFERROR(D8/B8,0) -> 0.019849728 | F8: ='Fictional Inputs'!D8 -> 13606000 | G8: ='Fictional Inputs'!E8 -> 13262000 | H8: =F8-G8 -> 344000 | I8: =B8-F8 -> 4001496 | J8: =C8-G8 -> 4695000 | K8: =J8-I8 -> 693504 | L8: =IFERROR(J8/C8,0) -> 0.26145793 | M8: =J8 -> 4695000 | N8: ='Fictional Inputs'!F8 -> 17647000 | O8: =IFERROR((C8-N8)/N8,0) -> 0.017566725
A9: ='Fictional Inputs'!A9 -> Jun | B9: ='Fictional Inputs'!B9 -> 18631161 | C9: ='Fictional Inputs'!C9 -> 18911000 | D9: =C9-B9 -> 279839 | E9: =IFERROR(D9/B9,0) -> 0.015019944 | F9: ='Fictional Inputs'!D9 -> 14311000 | G9: ='Fictional Inputs'!E9 -> 14926000 | H9: =F9-G9 -> -615000 | I9: =B9-F9 -> 4320161 | J9: =C9-G9 -> 3985000 | K9: =J9-I9 -> -335161 | L9: =IFERROR(J9/C9,0) -> 0.21072392 | M9: =J9 -> 3985000 | N9: ='Fictional Inputs'!F9 -> 18291000 | O9: =IFERROR((C9-N9)/N9,0) -> 0.033896452
A10: ='Fictional Inputs'!A10 -> Jul | B10: ='Fictional Inputs'!B10 -> 18632127 | C10: ='Fictional Inputs'!C10 -> 18992000 | D10: =C10-B10 -> 359873 | E10: =IFERROR(D10/B10,0) -> 0.019314649 | F10: ='Fictional Inputs'!D10 -> 14563000 | G10: ='Fictional Inputs'!E10 -> 13956000 | H10: =F10-G10 -> 607000 | I10: =B10-F10 -> 4069127 | J10: =C10-G10 -> 5036000 | K10: =J10-I10 -> 966873 | L10: =IFERROR(J10/C10,0) -> 0.26516428 | M10: =J10 -> 5036000 | N10: ='Fictional Inputs'!F10 -> 19152000 | O10: =IFERROR((C10-N10)/N10,0) -> -0.0083542189
A11: ='Fictional Inputs'!A11 -> Aug | B11: ='Fictional Inputs'!B11 -> 17918510 | C11: ='Fictional Inputs'!C11 -> 16857000 | D11: =C11-B11 -> -1061510 | E11: =IFERROR(D11/B11,0) -> -0.059240975 | F11: ='Fictional Inputs'!D11 -> 13648000 | G11: ='Fictional Inputs'!E11 -> 13099000 | H11: =F11-G11 -> 549000 | I11: =B11-F11 -> 4270510 | J11: =C11-G11 -> 3758000 | K11: =J11-I11 -> -512510 | L11: =IFERROR(J11/C11,0) -> 0.22293409 | M11: =J11 -> 3758000 | N11: ='Fictional Inputs'!F11 -> 18490000 | O11: =IFERROR((C11-N11)/N11,0) -> -0.08831801
A12: ='Fictional Inputs'!A12 -> Sep | B12: ='Fictional Inputs'!B12 -> 18974611 | C12: ='Fictional Inputs'!C12 -> 20040000 | D12: =C12-B12 -> 1065389 | E12: =IFERROR(D12/B12,0) -> 0.056148134 | F12: ='Fictional Inputs'!D12 -> 13983000 | G12: ='Fictional Inputs'!E12 -> 15393000 | H12: =F12-G12 -> -1410000 | I12: =B12-F12 -> 4991611 | J12: =C12-G12 -> 4647000 | K12: =J12-I12 -> -344611 | L12: =IFERROR(J12/C12,0) -> 0.23188623 | M12: =J12 -> 4647000 | N12: ='Fictional Inputs'!F12 -> 19225000 | O12: =IFERROR((C12-N12)/N12,0) -> 0.042392718
A13: ='Fictional Inputs'!A13 -> Oct | B13: ='Fictional Inputs'!B13 -> 19648856 | C13: ='Fictional Inputs'!C13 -> 20800000 | D13: =C13-B13 -> 1151144 | E13: =IFERROR(D13/B13,0) -> 0.058585803 | F13: ='Fictional Inputs'!D13 -> 15309000 | G13: ='Fictional Inputs'!E13 -> 16135000 | H13: =F13-G13 -> -826000 | I13: =B13-F13 -> 4339856 | J13: =C13-G13 -> 4665000 | K13: =J13-I13 -> 325144 | L13: =IFERROR(J13/C13,0) -> 0.22427885 | M13: =J13 -> 4665000 | N13: ='Fictional Inputs'!F13 -> 20255000 | O13: =IFERROR((C13-N13)/N13,0) -> 0.026906937
A14: ='Fictional Inputs'!A14 -> Nov | B14: ='Fictional Inputs'!B14 -> 18962586 | C14: ='Fictional Inputs'!C14 -> 17582000 | D14: =C14-B14 -> -1380586 | E14: =IFERROR(D14/B14,0) -> -0.072805787 | F14: ='Fictional Inputs'!D14 -> 14796000 | G14: ='Fictional Inputs'!E14 -> 13667000 | H14: =F14-G14 -> 1129000 | I14: =B14-F14 -> 4166586 | J14: =C14-G14 -> 3915000 | K14: =J14-I14 -> -251586 | L14: =IFERROR(J14/C14,0) -> 0.22267091 | M14: =J14 -> 3915000 | N14: ='Fictional Inputs'!F14 -> 18555000 | O14: =IFERROR((C14-N14)/N14,0) -> -0.052438696
A15: ='Fictional Inputs'!A15 -> Dec | B15: ='Fictional Inputs'!B15 -> 20007349 | C15: ='Fictional Inputs'!C15 -> 20354000 | D15: =C15-B15 -> 346651 | E15: =IFERROR(D15/B15,0) -> 0.017326183 | F15: ='Fictional Inputs'!D15 -> 15399000 | G15: ='Fictional Inputs'!E15 -> 15411000 | H15: =F15-G15 -> -12000 | I15: =B15-F15 -> 4608349 | J15: =C15-G15 -> 4943000 | K15: =J15-I15 -> 334651 | L15: =IFERROR(J15/C15,0) -> 0.24285153 | M15: =J15 -> 4943000 | N15: ='Fictional Inputs'!F15 -> 20074000 | O15: =IFERROR((C15-N15)/N15,0) -> 0.013948391
A17: FY TOTAL | B17: =SUM(B4:B15) -> 217160113 | C17: =SUM(C4:C15) -> 217240000 | D17: =SUM(D4:D15) -> 79887 | E17: =IFERROR(D17/B17,0) -> 0.00036787142 | F17: =SUM(F4:F15) -> 165607000 | G17: =SUM(G4:G15) -> 165854000 | H17: =SUM(H4:H15) -> -247000 | I17: =SUM(I4:I15) -> 51553113 | J17: =SUM(J4:J15) -> 51386000 | K17: =SUM(K4:K15) -> -167113 | L17: =IFERROR(J17/C17,0) -> 0.23654023 | M17: =SUM(M4:M15) -> 51386000 | N17: =SUM(N4:N15) -> 219140000 | O17: =IFERROR((C17-N17)/N17,0) -> -0.0086702565

Sheet Fictional Inputs
A1: FY2026 FICTIONAL FINANCIAL INPUTS
A3: Month | B3: Revenue Budget (RM) | C3: Revenue Actual (RM) | D3: Cost Budget (RM) | E3: Cost Actual (RM) | F3: Revenue Forecast (RM) | G3: Cost Forecast (RM)
A4: Jan | B4: 16282605 | C4: 16639000 | D4: 12112000 | E4: 13109000 | F4: 16282000 | G4: 12537000
A5: Feb | B5: 16753705 | C5: 15433000 | D5: 12453000 | E5: 12161000 | F5: 17155000 | G5: 13209000
A6: Mar | B6: 16325623 | C6: 16667000 | D6: 12503000 | E6: 12152000 | F6: 16131000 | G6: 12421000
A7: Apr | B7: 17415484 | C7: 17008000 | D7: 12924000 | E7: 12583000 | F7: 17883000 | G7: 13770000
A8: May | B8: 17607496 | C8: 17957000 | D8: 13606000 | E8: 13262000 | F8: 17647000 | G8: 13588000
A9: Jun | B9: 18631161 | C9: 18911000 | D9: 14311000 | E9: 14926000 | F9: 18291000 | G9: 14084000
A10: Jul | B10: 18632127 | C10: 18992000 | D10: 14563000 | E10: 13956000 | F10: 19152000 | G10: 14747000
A11: Aug | B11: 17918510 | C11: 16857000 | D11: 13648000 | E11: 13099000 | F11: 18490000 | G11: 14237000
A12: Sep | B12: 18974611 | C12: 20040000 | D12: 13983000 | E12: 15393000 | F12: 19225000 | G12: 14803000
A13: Oct | B13: 19648856 | C13: 20800000 | D13: 15309000 | E13: 16135000 | F13: 20255000 | G13: 15596000
A14: Nov | B14: 18962586 | C14: 17582000 | D14: 14796000 | E14: 13667000 | F14: 18555000 | G14: 14287000
A15: Dec | B15: 20007349 | C15: 20354000 | D15: 15399000 | E15: 15411000 | F15: 20074000 | G15: 15457000
A17: Data classification | B17: 100% fictional data — for portfolio demonstration only
A18: Cost definition | B18: Illustrative project direct costs + operating costs combined
A19: EBITDA proxy | B19: Revenue minus modeled cost; excludes financing, tax, D&A (not separately modeled)
A20: Forecast definition | B20: Independent fictional full-year monthly forecast for comparison

Sheet Read Me
A1: PROJECT 01 | FINANCIAL PERFORMANCE DASHBOARD
A3: Purpose | B3: Demonstrate budget-versus-actual review, forecast tracking, margins and executive insights.
A4: Dataset | B4: Synthetic FY2026 monthly values only. Not actual results of any company.
A5: 1 — Inputs | B5: Change blue-number cells on Fictional Inputs. All calculations update.
A6: 2 — Analysis | B6: Monthly Performance calculates revenue, gross profit, favorable cost variance and forecast comparison.
A7: 3 — Dashboard | B7: Executive Dashboard displays formula-driven KPIs, trends and management commentary.
A8: Revenue variance | B8: Actual revenue minus budget; positive is favorable.
A9: Cost variance | B9: Budget cost minus actual cost; positive is favorable.
A10: Gross profit | B10: Revenue minus illustrative modeled costs.
A11: Gross profit margin | B11: Gross profit divided by actual revenue.
A12: EBITDA proxy | B12: Equals modeled gross profit; NOT a true EBITDA reconciliation without separate operating expenses.
A13: Forecast variance | B13: Actual revenue divided by forecast revenue, minus one.
A14: Units | B14: Raw source sheets in RM; dashboard financial KPIs in RM millions.
... A16: Confidentiality | B16: Do not replace sample inputs with nonpublic employer data.
